api_stream_client/__init__.py
api_stream_client/archival.py
api_stream_client/lsdb.py
api_stream_client/ospfclient.py
api_stream_client/websockets_server.py
frr_ospf_api_stream_client-1.1.0.dist-info/METADATA
frr_ospf_api_stream_client-1.1.0.dist-info/WHEEL
frr_ospf_api_stream_client-1.1.0.dist-info/entry_points.txt
frr_ospf_api_stream_client-1.1.0.dist-info/top_level.txt
frr_ospf_api_stream_client-1.1.0.dist-info/RECORD
