Metadata-Version: 2.1
Name: frr-ospf-api-stream-client
Version: 1.1.0
Summary: Stateful pure-python API client for the FRR OSPF API to generate network snapshots and diff-based event streams
Author-email: Andrew Dickinson <andrew.dickinson.0216@gmail.com>
License:                     GNU GENERAL PUBLIC LICENSE
Project-URL: repository, https://github.com/Andrew-Dickinson/frr-ospf-api-stream-client
Classifier: License :: OSI Approved :: GNU Lesser General Public License v2 (LGPLv2)
Classifier: Programming Language :: Python :: 3
Classifier: Operating System :: OS Independent
Requires-Dist: netaddr==1.3.*
Requires-Dist: frozendict==2.4.*
Requires-Dist: jsondiff==2.2.*
Requires-Dist: autobahn==24.4.*
Requires-Dist: apscheduler==3.11.*
Provides-Extra: test
Requires-Dist: pytest>=6; extra == "test"
Requires-Dist: coverage; extra == "test"
Provides-Extra: dev
Requires-Dist: build; extra == "dev"
Requires-Dist: twine; extra == "dev"
